cellamander/__init__.py
cellamander/cellamander.py
cellamander-0.0.1.dist-info/METADATA
cellamander-0.0.1.dist-info/WHEEL
cellamander-0.0.1.dist-info/licenses/AUTHORS
cellamander-0.0.1.dist-info/licenses/LICENSE
cellamander-0.0.1.dist-info/RECORD
